lpot/__init__.py
lpot/benchmark.py
lpot/objective.py
lpot/pruning.py
lpot/quantization.py
lpot/version.py
lpot/adaptor/__init__.py
lpot/adaptor/adaptor.py
lpot/adaptor/mxnet.py
lpot/adaptor/mxnet.yaml
lpot/adaptor/onnxrt.py
lpot/adaptor/onnxrt_integer.yaml
lpot/adaptor/onnxrt_qlinear.yaml
lpot/adaptor/pytorch.py
lpot/adaptor/pytorch_cpu.yaml
lpot/adaptor/pytorch_gpu.yaml
lpot/adaptor/pytorch_ipex.yaml
lpot/adaptor/query.py
lpot/adaptor/tensorflow.py
lpot/adaptor/tensorflow.yaml
lpot/adaptor/tensorflow_itex.yaml
lpot/adaptor/mxnet_utils/__init__.py
lpot/adaptor/mxnet_utils/util.py
lpot/adaptor/ox_utils/__init__.py
lpot/adaptor/ox_utils/onnx_quantizer.py
lpot/adaptor/ox_utils/onnxrt_mid.py
lpot/adaptor/ox_utils/registry.py
lpot/adaptor/ox_utils/util.py
lpot/adaptor/ox_utils/operators/__init__.py
lpot/adaptor/ox_utils/operators/activation.py
lpot/adaptor/ox_utils/operators/attention.py
lpot/adaptor/ox_utils/operators/base_operator.py
lpot/adaptor/ox_utils/operators/binary_op.py
lpot/adaptor/ox_utils/operators/conv.py
lpot/adaptor/ox_utils/operators/embed_layernorm.py
lpot/adaptor/ox_utils/operators/gather.py
lpot/adaptor/ox_utils/operators/gavgpool.py
lpot/adaptor/ox_utils/operators/lstm.py
lpot/adaptor/ox_utils/operators/matmul.py
lpot/adaptor/ox_utils/operators/maxpool.py
lpot/adaptor/ox_utils/operators/pad.py
lpot/adaptor/ox_utils/operators/split.py
lpot/adaptor/tf_utils/__init__.py
lpot/adaptor/tf_utils/graph_converter.py
lpot/adaptor/tf_utils/graph_converter_without_calib.py
lpot/adaptor/tf_utils/util.py
lpot/adaptor/tf_utils/graph_rewriter/__init__.py
lpot/adaptor/tf_utils/graph_rewriter/graph_base.py
lpot/adaptor/tf_utils/graph_rewriter/graph_util.py
lpot/adaptor/tf_utils/graph_rewriter/bf16/__init__.py
lpot/adaptor/tf_utils/graph_rewriter/bf16/bf16_convert.py
lpot/adaptor/tf_utils/graph_rewriter/generic/__init__.py
lpot/adaptor/tf_utils/graph_rewriter/generic/convert_add_to_biasadd.py
lpot/adaptor/tf_utils/graph_rewriter/generic/convert_layout.py
lpot-1.6.dist-info/LICENSE
lpot-1.6.dist-info/METADATA
lpot-1.6.dist-info/WHEEL
lpot-1.6.dist-info/entry_points.txt
lpot-1.6.dist-info/top_level.txt
lpot-1.6.dist-info/RECORD
