Metadata-Version: 2.1
Name: lpot
Version: 1.6
Summary: Repository of Intel® Low Precision Optimization Tool
Home-page: https://github.com/intel/lpot
Author: Intel MLP/MLPC Team
Author-email: feng.tian@intel.com, chuanqi.wang@intel.com, pengxin.yuan@intel.com, guoming.zhang@intel.com, haihao.shen@intel.com, jiong.gong@intel.com, xi2.chen@intel.com
License: UNKNOWN
Keywords: quantization,auto-tuning,post-training static quantization,post-training dynamic quantization,quantization-aware training,tuning strategy
Platform: UNKNOWN
Classifier: Intended Audience :: Science/Research
Classifier: Programming Language :: Python :: 3
Classifier: Topic :: Scientific/Engineering :: Artificial Intelligence
Requires-Python: >=3.6.0
Requires-Dist: numpy
Requires-Dist: pyyaml
Requires-Dist: scikit-learn
Requires-Dist: schema
Requires-Dist: py-cpuinfo
Requires-Dist: hyperopt
Requires-Dist: pandas
Requires-Dist: pycocotools
Requires-Dist: opencv-python
Requires-Dist: requests
Requires-Dist: Flask-Cors
Requires-Dist: Flask-SocketIO
Requires-Dist: Flask
Requires-Dist: gevent-websocket
Requires-Dist: gevent
Requires-Dist: psutil
Requires-Dist: Pillow
Requires-Dist: sigopt
Requires-Dist: prettytable
